Workbook

Sheet São Paulo
A1: Evolução de receitas e despesas - São Paulo/SP
A2: Valores em R$ - Preço reais deflacionados pelo IPCA/IBGE
A3: Ano | B3: Receita Nominal (R$) | C3: Despesa Nominal (R$) | D3: IPCA | E3: Receita Real (R$) | F3: Despesa Real (R$) | G3: Saldo Real (R$)
A4: 2016 | B4: 4.9608274e+10 | C4: 4.9422519e+10 | D4: 0.0629 | E4: =B4/(1+D$4) -> 4.6672569e+10 | F4: =C4/(1+D$6) -> 4.7636163e+10 | G4: =E4-F4 -> -9.6359376e+08
A5: 2017 | B5: 5.4010997e+10 | C5: 5.1414029e+10 | D5: 0.0295 | E5: =B5/(1+D$4) -> 5.0814749e+10 | F5: =C5/(1+D$6) -> 4.9555691e+10 | G5: =E5-F5 -> 1.2590584e+09
A6: 2018 | B6: 5.7383494e+10 | C6: 5.4157142e+10 | D6: 0.0375 | E6: =B6/(1+D$4) -> 5.3987669e+10 | F6: =C6/(1+D$6) -> 5.2199655e+10 | G6: =E6-F6 -> 1.7880145e+09
A7: 2019 | B7: 65802065976 | C7: 5.9389424e+10 | D7: 0.0431 | E7: =B7/(1+D$4) -> 6.190805e+10 | F7: =C7/(1+D$6) -> 5.7242819e+10 | G7: =E7-F7 -> 4.6652311e+09
A8: 2020 | B8: 69029896989 | C8: 6.4915337e+10 | D8: 0.0452 | E8: =B8/(1+D$4) -> 6.4944865e+10 | F8: =C8/(1+D$6) -> 6.2569e+10 | G8: =E8-F8 -> 2.3758651e+09
A9: 2021 | B9: 79516385335 | C9: 7.3423283e+10 | D9: 0.1006 | E9: =B9/(1+D$4) -> 7.4810787e+10 | F9: =C9/(1+D$6) -> 7.076943e+10 | G9: =E9-F9 -> 4.0413573e+09
A10: 2022 | B10: 95789912729 | C10: 9.108834e+10 | D10: 0.0579 | E10: =B10/(1+D$4) -> 9.0121284e+10 | F10: =C10/(1+D$6) -> 8.7795991e+10 | G10: =E10-F10 -> 2.3252934e+09
A11: 2023 | B11: 103907650084 | C11: 1.0682921e+11 | D11: 0.0462 | E11: =B11/(1+D$4) -> 9.7758632e+10 | F11: =C11/(1+D$6) -> 1.0296792e+11 | G11: =E11-F11 -> -5.2092847e+09
A12: 2024 | B12: 121320658641 | C12: 1.2390918e+11 | D12: 0.0483 | E12: =B12/(1+D$4) -> 1.1414118e+11 | F12: =C12/(1+D$6) -> 1.1943054e+11 | G12: =E12-F12 -> -5.2893599e+09
A13: 2025 | B13: 127308730790 | C13: 1.2357181e+11 | D13: 0.0426 | E13: =B13/(1+D$4) -> 1.1977489e+11 | F13: =C13/(1+D$6) -> 1.1910536e+11 | G13: =E13-F13 -> 6.6953435e+08

Sheet Campinas
A1: Evolução de receitas e despesas - Campinas/SP
A2: Valores em R$ - Preço reais deflacionados pelo IPCA/IBGE
A3: Ano | B3: Receita Nominal (R$) | C3: Despesa Nominal (R$) | D3: IPCA | E3: Receita Real (R$) | F3: Despesa Real (R$) | G3: Saldo Real (R$)
A4: 2016 | B4: 4.4925147e+09 | C4: 4.4968621e+09 | D4: 0.0629 | E4: =B4/(1+D$4) -> 4.2266579e+09 | F4: =C4/(1+D$6) -> 4.3343249e+09 | G4: =E4-F4 -> -1.07667e+08
A5: 2017 | B5: 4614990762 | C5: 4.7199757e+09 | D5: 0.0295 | E5: =B5/(1+D$4) -> 4.3418861e+09 | F5: =C5/(1+D$6) -> 4.5493742e+09 | G5: =E5-F5 -> -2.0748803e+08
A6: 2018 | B6: 5.0734264e+09 | C6: 4.8836522e+09 | D6: 0.0375 | E6: =B6/(1+D$4) -> 4.7731926e+09 | F6: =C6/(1+D$6) -> 4.7071346e+09 | G6: =E6-F6 -> 66057972
A7: 2019 | B7: 6119036575 | C7: 5.5249875e+09 | D7: 0.0431 | E7: =B7/(1+D$4) -> 5.7569259e+09 | F7: =C7/(1+D$6) -> 5.3252892e+09 | G7: =E7-F7 -> 4.3163678e+08
A8: 2020 | B8: 6456830874 | C8: 5.6826451e+09 | D8: 0.0452 | E8: =B8/(1+D$4) -> 6.0747303e+09 | F8: =C8/(1+D$6) -> 5.4772483e+09 | G8: =E8-F8 -> 5.9748206e+08
A9: 2021 | B9: 7341521312 | C9: 6.5108144e+09 | D9: 0.1006 | E9: =B9/(1+D$4) -> 6.9070668e+09 | F9: =C9/(1+D$6) -> 6.2754838e+09 | G9: =E9-F9 -> 6.3158302e+08
A10: 2022 | B10: 8143599535 | C10: 7.2195424e+09 | D10: 0.0579 | E10: =B10/(1+D$4) -> 7.6616799e+09 | F10: =C10/(1+D$6) -> 6.9585951e+09 | G10: =E10-F10 -> 7.0308478e+08
A11: 2023 | B11: 8751568077 | C11: 8.3245961e+09 | D11: 0.0462 | E11: =B11/(1+D$4) -> 8.2336702e+09 | F11: =C11/(1+D$6) -> 8.0237071e+09 | G11: =E11-F11 -> 2.0996311e+08
A12: 2024 | B12: 10221807837 | C12: 9.3632404e+09 | D12: 0.0483 | E12: =B12/(1+D$4) -> 9.6169045e+09 | F12: =C12/(1+D$6) -> 9.02481e+09 | G12: =E12-F12 -> 5.9209453e+08
A13: 2025 | B13: 11497786866 | C13: 1.0666515e+10 | D13: 0.0426 | E13: =B13/(1+D$4) -> 1.0817374e+10 | F13: =C13/(1+D$6) -> 1.0280979e+10 | G13: =E13-F13 -> 5.3639546e+08

Sheet Comparativo
A1: COMPARATIVO — SÃO PAULO × CAMPINAS | Valores Reais em R$
B2: SÃO PAULO | E2: CAMPINAS | H2: DIFERENÇA
A3: Ano | B3: Receita | C3: Despesa | D3: Saldo | E3: Receita | F3: Despesa | G3: Saldo | H3: Receita | I3: Despesa | J3: Saldo
A4: 2016 | B4: ='São Paulo'!E4 -> 4.6672569e+10 | C4: ='São Paulo'!F4 -> 4.7636163e+10 | D4: =B4-C4 -> -9.6359376e+08 | E4: =Campinas!E4 -> 4.2266579e+09 | F4: =Campinas!F4 -> 4.3343249e+09 | G4: =E4-F4 -> -1.07667e+08 | H4: =B4-E4 -> 4.2445911e+10 | I4: =C4-F4 -> 4.3301838e+10 | J4: =H4-I4 -> -8.5592676e+08
A5: 2017 | B5: ='São Paulo'!E5 -> 5.0814749e+10 | C5: ='São Paulo'!F5 -> 4.9555691e+10 | D5: =B5-C5 -> 1.2590584e+09 | E5: =Campinas!E5 -> 4.3418861e+09 | F5: =Campinas!F5 -> 4.5493742e+09 | G5: =E5-F5 -> -2.0748803e+08 | H5: =B5-E5 -> 4.6472863e+10 | I5: =C5-F5 -> 4.5006317e+10 | J5: =H5-I5 -> 1.4665464e+09
A6: 2018 | B6: ='São Paulo'!E6 -> 5.3987669e+10 | C6: ='São Paulo'!F6 -> 5.2199655e+10 | D6: =B6-C6 -> 1.7880145e+09 | E6: =Campinas!E6 -> 4.7731926e+09 | F6: =Campinas!F6 -> 4.7071346e+09 | G6: =E6-F6 -> 66057972 | H6: =B6-E6 -> 4.9214477e+10 | I6: =C6-F6 -> 4.749252e+10 | J6: =H6-I6 -> 1.7219565e+09
A7: 2019 | B7: ='São Paulo'!E7 -> 6.190805e+10 | C7: ='São Paulo'!F7 -> 5.7242819e+10 | D7: =B7-C7 -> 4.6652311e+09 | E7: =Campinas!E7 -> 5.7569259e+09 | F7: =Campinas!F7 -> 5.3252892e+09 | G7: =E7-F7 -> 4.3163678e+08 | H7: =B7-E7 -> 5.6151124e+10 | I7: =C7-F7 -> 5.1917529e+10 | J7: =H7-I7 -> 4.2335943e+09
A8: 2020 | B8: ='São Paulo'!E8 -> 6.4944865e+10 | C8: ='São Paulo'!F8 -> 6.2569e+10 | D8: =B8-C8 -> 2.3758651e+09 | E8: =Campinas!E8 -> 6.0747303e+09 | F8: =Campinas!F8 -> 5.4772483e+09 | G8: =E8-F8 -> 5.9748206e+08 | H8: =B8-E8 -> 5.8870135e+10 | I8: =C8-F8 -> 5.7091752e+10 | J8: =H8-I8 -> 1.778383e+09
A9: 2021 | B9: ='São Paulo'!E9 -> 7.4810787e+10 | C9: ='São Paulo'!F9 -> 7.076943e+10 | D9: =B9-C9 -> 4.0413573e+09 | E9: =Campinas!E9 -> 6.9070668e+09 | F9: =Campinas!F9 -> 6.2754838e+09 | G9: =E9-F9 -> 6.3158302e+08 | H9: =B9-E9 -> 6.790372e+10 | I9: =C9-F9 -> 6.4493946e+10 | J9: =H9-I9 -> 3.4097743e+09
A10: 2022 | B10: ='São Paulo'!E10 -> 9.0121284e+10 | C10: ='São Paulo'!F10 -> 8.7795991e+10 | D10: =B10-C10 -> 2.3252934e+09 | E10: =Campinas!E10 -> 7.6616799e+09 | F10: =Campinas!F10 -> 6.9585951e+09 | G10: =E10-F10 -> 7.0308478e+08 | H10: =B10-E10 -> 8.2459604e+10 | I10: =C10-F10 -> 8.0837395e+10 | J10: =H10-I10 -> 1.6222086e+09
A11: 2023 | B11: ='São Paulo'!E11 -> 9.7758632e+10 | C11: ='São Paulo'!F11 -> 1.0296792e+11 | D11: =B11-C11 -> -5.2092847e+09 | E11: =Campinas!E11 -> 8.2336702e+09 | F11: =Campinas!F11 -> 8.0237071e+09 | G11: =E11-F11 -> 2.0996311e+08 | H11: =B11-E11 -> 8.9524962e+10 | I11: =C11-F11 -> 9.494421e+10 | J11: =H11-I11 -> -5.4192478e+09
A12: 2024 | B12: ='São Paulo'!E12 -> 1.1414118e+11 | C12: ='São Paulo'!F12 -> 1.1943054e+11 | D12: =B12-C12 -> -5.2893599e+09 | E12: =Campinas!E12 -> 9.6169045e+09 | F12: =Campinas!F12 -> 9.02481e+09 | G12: =E12-F12 -> 5.9209453e+08 | H12: =B12-E12 -> 1.0452427e+11 | I12: =C12-F12 -> 1.1040573e+11 | J12: =H12-I12 -> -5.8814545e+09
A13: 2025 | B13: ='São Paulo'!E13 -> 1.1977489e+11 | C13: ='São Paulo'!F13 -> 1.1910536e+11 | D13: =B13-C13 -> 6.6953435e+08 | E13: =Campinas!E13 -> 1.0817374e+10 | F13: =Campinas!F13 -> 1.0280979e+10 | G13: =E13-F13 -> 5.3639546e+08 | H13: =B13-E13 -> 1.0895752e+11 | I13: =C13-F13 -> 1.0882438e+11 | J13: =H13-I13 -> 1.3313889e+08
A15: Fonte: SICONFI/STN. Deflator: IPCA/IBGE.

Sheet Gráfico
A1: DADOS PARA GRÁFICOS — Receitas e Despesas Reais
A2: Ano | B2: São Paulo Receita | C2: São Paulo Despesa | D2: Campinas Receita | E2: Campinas Despesa
A3: 2016 | B3: =Comparativo!B4 -> 4.6672569e+10 | C3: =Comparativo!C4 -> 4.7636163e+10 | D3: =Comparativo!E4 -> 4.2266579e+09 | E3: =Comparativo!F4 -> 4.3343249e+09
A4: 2017 | B4: =Comparativo!B5 -> 5.0814749e+10 | C4: =Comparativo!C5 -> 4.9555691e+10 | D4: =Comparativo!E5 -> 4.3418861e+09 | E4: =Comparativo!F5 -> 4.5493742e+09
A5: 2018 | B5: =Comparativo!B6 -> 5.3987669e+10 | C5: =Comparativo!C6 -> 5.2199655e+10 | D5: =Comparativo!E6 -> 4.7731926e+09 | E5: =Comparativo!F6 -> 4.7071346e+09
A6: 2019 | B6: =Comparativo!B7 -> 6.190805e+10 | C6: =Comparativo!C7 -> 5.7242819e+10 | D6: =Comparativo!E7 -> 5.7569259e+09 | E6: =Comparativo!F7 -> 5.3252892e+09
A7: 2020 | B7: =Comparativo!B8 -> 6.4944865e+10 | C7: =Comparativo!C8 -> 6.2569e+10 | D7: =Comparativo!E8 -> 6.0747303e+09 | E7: =Comparativo!F8 -> 5.4772483e+09
A8: 2021 | B8: =Comparativo!B9 -> 7.4810787e+10 | C8: =Comparativo!C9 -> 7.076943e+10 | D8: =Comparativo!E9 -> 6.9070668e+09 | E8: =Comparativo!F9 -> 6.2754838e+09
A9: 2022 | B9: =Comparativo!B10 -> 9.0121284e+10 | C9: =Comparativo!C10 -> 8.7795991e+10 | D9: =Comparativo!E10 -> 7.6616799e+09 | E9: =Comparativo!F10 -> 6.9585951e+09
A10: 2023 | B10: =Comparativo!B11 -> 9.7758632e+10 | C10: =Comparativo!C11 -> 1.0296792e+11 | D10: =Comparativo!E11 -> 8.2336702e+09 | E10: =Comparativo!F11 -> 8.0237071e+09
A11: 2024 | B11: =Comparativo!B12 -> 1.1414118e+11 | C11: =Comparativo!C12 -> 1.1943054e+11 | D11: =Comparativo!E12 -> 9.6169045e+09 | E11: =Comparativo!F12 -> 9.02481e+09
A12: 2025 | B12: =Comparativo!B13 -> 1.1977489e+11 | C12: =Comparativo!C13 -> 1.1910536e+11 | D12: =Comparativo!E13 -> 1.0817374e+10 | E12: =Comparativo!F13 -> 1.0280979e+10
